node_chatgpt_api/__init__.py
node_chatgpt_api/main.py
node_chatgpt_api/helpers/__init__.py
node_chatgpt_api/helpers/install.py
node_chatgpt_api/helpers/log.py
node_chatgpt_api/types/__init__.py
node_chatgpt_api/types/message.py
node_chatgpt_api/types/response.py
node_chatgpt_api-1.0.1.dist-info/LICENSE
node_chatgpt_api-1.0.1.dist-info/METADATA
node_chatgpt_api-1.0.1.dist-info/WHEEL
node_chatgpt_api-1.0.1.dist-info/top_level.txt
node_chatgpt_api-1.0.1.dist-info/RECORD
