Metadata-Version: 2.1
Name: node-chatgpt-api
Version: 1.0.1
Home-page: https://github.com/oskardotglobal/node-chatgpt-api.py
Author: Oskar Manhart
Author-email: me@oskar.global
License: MIT
License-File: LICENSE
Requires-Dist: nodejs-bin (==18.4.0a4)
Requires-Dist: requests (==2.28.2)
Requires-Dist: cache3 (==0.4.2)
